bounding_ai_tool/__init__.py
bounding_ai_tool/__main__.py
bounding_ai_tool/command_line.py
bounding_ai_tool/debug.py
bounding_ai_tool/debug_startup.py
bounding_ai_tool/run.py
bounding_ai_tool/version.py
bounding_ai_tool/api/__init__.py
bounding_ai_tool/api/camera/__init__.py
bounding_ai_tool/api/constructor/__init__.py
bounding_ai_tool/api/filter/__init__.py
bounding_ai_tool/api/lighting/__init__.py
bounding_ai_tool/api/loader/__init__.py
bounding_ai_tool/api/material/__init__.py
bounding_ai_tool/api/math/__init__.py
bounding_ai_tool/api/object/__init__.py
bounding_ai_tool/api/postprocessing/__init__.py
bounding_ai_tool/api/renderer/__init__.py
bounding_ai_tool/api/sampler/__init__.py
bounding_ai_tool/api/types/__init__.py
bounding_ai_tool/api/utility/__init__.py
bounding_ai_tool/api/world/__init__.py
bounding_ai_tool/api/writer/__init__.py
bounding_ai_tool/external/__init__.py
bounding_ai_tool/external/vhacd/__init__.py
bounding_ai_tool/external/vhacd/decompose.py
bounding_ai_tool/python/__init__.py
bounding_ai_tool/python/camera/CameraUtility.py
bounding_ai_tool/python/camera/CameraValidation.py
bounding_ai_tool/python/camera/LensDistortionUtility.py
bounding_ai_tool/python/camera/__init__.py
bounding_ai_tool/python/constructor/RandomRoomConstructor.py
bounding_ai_tool/python/constructor/__init__.py
bounding_ai_tool/python/filter/Filter.py
bounding_ai_tool/python/filter/__init__.py
bounding_ai_tool/python/lighting/SuncgLighting.py
bounding_ai_tool/python/lighting/SurfaceLighting.py
bounding_ai_tool/python/lighting/__init__.py
bounding_ai_tool/python/loader/AMASSLoader.py
bounding_ai_tool/python/loader/BlendLoader.py
bounding_ai_tool/python/loader/BopLoader.py
bounding_ai_tool/python/loader/CCMaterialLoader.py
bounding_ai_tool/python/loader/Front3DLoader.py
bounding_ai_tool/python/loader/HavenEnvironmentLoader.py
bounding_ai_tool/python/loader/HavenMaterialLoader.py
bounding_ai_tool/python/loader/IKEALoader.py
bounding_ai_tool/python/loader/ObjectLoader.py
bounding_ai_tool-0.3.0.dist-info/LICENSE
bounding_ai_tool-0.3.0.dist-info/METADATA
bounding_ai_tool-0.3.0.dist-info/WHEEL
bounding_ai_tool-0.3.0.dist-info/entry_points.txt
bounding_ai_tool-0.3.0.dist-info/top_level.txt
bounding_ai_tool-0.3.0.dist-info/RECORD
