Metadata-Version: 2.1
Name: bounding-ai-tool
Version: 0.3.0
Summary: UNKNOWN
Home-page: https://github.com/Simerse/bounding_ai_tool
Author: Simerse
License: UNKNOWN
Platform: UNKNOWN
License-File: LICENSE
Requires-Dist: setuptools
Requires-Dist: pyyaml
Requires-Dist: requests
Requires-Dist: matplotlib
Requires-Dist: numpy
Requires-Dist: Pillow
Requires-Dist: h5py
Requires-Dist: progressbar
